{
    "Date": "Dec 2X",
    "patient_information": {
        "patient_id": "555 Aeponed Dajs Pe 07 DrC 2X One Complete Blood CBCY Count Investigation Reference Value Result Unit Primory Sample Type Blood Hemogl Obin Hemoglobin 170 HBJ Tzs Lor Ssos Gial RBC Count Toial RBC S 55 Count Sz Mfcumm Blood Indices Packed Cell Volume PCV High 50 X St5S Gos Corpuscular Volume IMCVI 8775 835 101 Meon CeAig MCH 272 276 32 PG Latnes MCHIC 328 3257 345 Giol CECUaoled RDW 1316 1166 JA0 X S Count WAC Titat Count Sies 1i DL 1Ooo Ir L Fat 40001 9OOO Total WBC Cumm Differential WBC Count Neutrophils 50 TL 50 621 L Li Goa L 40L TAD 2o7 Lymphocyles T Eosinopils 00 06 T K Monocyies 00 10 Basophlls Go 02 X Platelet Count Plaletel Count Soodg Bordarline Sgooo SGooo Cumm Instrumentsh Fully Outomaled Celi Mlndroy Jo0 Counler Nisproation Funner Conim For Ancrme Thonls Relcrence End RCPont IDR ODL Hos Dr Vimal Shah Technician Dr Payal Shah Medical Lab MDs Pathologisly Eids Pathologiesy DMLIT EMlt Goanotd DN Or DCS Cozr F OO In Page DT Collection 0123456789 Samplec",
        "patient_name": null,
        "patient_sex": "Male",
        "patient_age": 21
    },
    "test_results": [
        {
            "test_name": "Hemoglobin",
            "result_value": 170,
            "unit_of_measurement": "HBJ Tzs Lor Ssos Gial",
            "reference_range": null
        },
        {
            "test_name": "RBC Count Toial RBC S",
            "result_value": 55,
            "unit_of_measurement": "Count Sz Mfcumm Blood Indices",
            "reference_range": null
        },
        {
            "test_name": "Packed Cell Volume PCV High",
            "result_value": 50,
            "unit_of_measurement": "X St5S Gos Corpuscular Volume IMCVI",
            "reference_range": null
        },
        {
            "test_name": "MCH",
            "result_value": 272,
            "unit_of_measurement": "Meon CeAig MCH",
            "reference_range": "276 32 PG Latnes"
        },
        {
            "test_name": "RDW",
            "result_value": 1316,
            "unit_of_measurement": "JA0 X S Count WAC Titat Count Sies",
            "reference_range": null
        },
        {
            "test_name": "Neutrophils",
            "result_value": 50,
            "unit_of_measurement": "TL 50 621 L Li Goa L",
            "reference_range": null
        },
        {
            "test_name": "Platelet Count Plaletel Count Soodg Bordarline",
            "result_value": 50000,
            "unit_of_measurement": "SGooo SGooo Cumm Instrumentsh Fully Outomaled",
            "reference_range": null
        }
    ]
}