{
    "Date": "125, Shivam M. Patel Mumbai By: Dr. Hiren Shah Yash 21 Years Ref. Count (CBC) Unit Age Sex: Male Blood Value PID: : 555 Complete Reference Result g/dl Blood Low 130-170 milicumm Inestigation Type Primary Sample 12.5 4.5-5.5 NEMOGLOEN Henosiobin (Hb) 5.2 40-50 fL COUNT High 83-101 pg RBC Total RBC count 57.5 27-32 g/dL BLOOD INDICES Volume (PCV) (MCV) 87.75 % Packed Cell Volume 27.2 325-345 14.0 cumm Mean Corpuscularv 11.6- alcul 32.8 MCH Calcul 13.6 40001000 MCHC 9000 50-62 RDW COUNT 20-40 WBC Total WBCC count WBC COUNT 60 00-06 00-10 DEFERENTALY 31 00-02 cumm Nestrohie tymphonres 7 410000 Eosinochis Borderline 150000 Monoores Basophils 150000 COUNT PLATELET Platelet Count counter Mindray 300 automated cell Intrumentse Fully confirmt for Anemia ****End of Report",
    "patient_information": {
        "patient_id": null,
        "patient_name": null,
        "patient_sex": "Male",
        "patient_age": "21 Years"
    },
    "test_results": [
        {
            "test_name": "Complete Reference Result",
            "result_value": "5.2",
            "unit_of_measurement": "g/dl",
            "reference_range": "40-50"
        },
        {
            "test_name": "RBC Total RBC count",
            "result_value": "57.5",
            "unit_of_measurement": "g/dL",
            "reference_range": "27-32"
        },
        {
            "test_name": "MCV",
            "result_value": "87.75%",
            "unit_of_measurement": "%",
            "reference_range": null
        },
        {
            "test_name": "MCH",
            "result_value": "13.6",
            "unit_of_measurement": "pg",
            "reference_range": "40-50"
        },
        {
            "test_name": "RDW COUNT",
            "result_value": null,
            "unit_of_measurement": "cumm",
            "reference_range": "20-40"
        },
        {
            "test_name": "WBC Total WBCC count WBC COUNT",
            "result_value": "60",
            "unit_of_measurement": null,
            "reference_range": "4.5-5.5"
        },
        {
            "test_name": "MCHC",
            "result_value": "9000",
            "unit_of_measurement": "mL",
            "reference_range": "50-62"
        },
        {
            "test_name": null,
            "result_value": null,
            "unit_of_measurement": null,
            "reference_range": null
        }
    ]
}